cobalt8/__init__.py
cobalt8/__version__.py
cobalt8/aes.py
cobalt8/autoupdate.py
cobalt8/cobalt8.py
cobalt8/scraper.py
cobalt8-0.0.3.dist-info/LICENSE
cobalt8-0.0.3.dist-info/METADATA
cobalt8-0.0.3.dist-info/WHEEL
cobalt8-0.0.3.dist-info/entry_points.txt
cobalt8-0.0.3.dist-info/top_level.txt
cobalt8-0.0.3.dist-info/RECORD
